AUTHORS
LICENCE
MANIFEST.in
README.rst
RELEASE-NOTES
app.fil
electrum-vtc
electrum-vtc.conf.sample
electrum-vtc.desktop
icons.qrc
setup-release.py
setup.py
Electrum_VTC.egg-info/PKG-INFO
Electrum_VTC.egg-info/SOURCES.txt
Electrum_VTC.egg-info/dependency_links.txt
Electrum_VTC.egg-info/requires.txt
Electrum_VTC.egg-info/top_level.txt
gui/__init__.py
gui/stdio.py
gui/text.py
gui/kivy/__init__.py
gui/kivy/i18n.py
gui/kivy/main_window.py
gui/kivy/nfc_scanner/__init__.py
gui/kivy/nfc_scanner/scanner_android.py
gui/kivy/nfc_scanner/scanner_dummy.py
gui/kivy/uix/__init__.py
gui/kivy/uix/combobox.py
gui/kivy/uix/context_menu.py
gui/kivy/uix/drawer.py
gui/kivy/uix/gridview.py
gui/kivy/uix/menus.py
gui/kivy/uix/qrcodewidget.py
gui/kivy/uix/screens.py
gui/kivy/uix/dialogs/__init__.py
gui/kivy/uix/dialogs/amount_dialog.py
gui/kivy/uix/dialogs/bump_fee_dialog.py
gui/kivy/uix/dialogs/checkbox_dialog.py
gui/kivy/uix/dialogs/checkpoint_dialog.py
gui/kivy/uix/dialogs/choice_dialog.py
gui/kivy/uix/dialogs/fee_dialog.py
gui/kivy/uix/dialogs/fx_dialog.py
gui/kivy/uix/dialogs/installwizard.py
gui/kivy/uix/dialogs/label_dialog.py
gui/kivy/uix/dialogs/nfc_transaction.py
gui/kivy/uix/dialogs/password_dialog.py
gui/kivy/uix/dialogs/qr_dialog.py
gui/kivy/uix/dialogs/qr_scanner.py
gui/kivy/uix/dialogs/question.py
gui/kivy/uix/dialogs/seed_options.py
gui/kivy/uix/dialogs/settings.py
gui/kivy/uix/dialogs/tx_dialog.py
gui/kivy/uix/dialogs/wallets.py
gui/qt/__init__.py
gui/qt/address_dialog.py
gui/qt/address_list.py
gui/qt/amountedit.py
gui/qt/console.py
gui/qt/contact_list.py
gui/qt/fee_slider.py
gui/qt/history_list.py
gui/qt/icons_rc.py
gui/qt/installwizard.py
gui/qt/invoice_list.py
gui/qt/main_window.py
gui/qt/network_dialog.py
gui/qt/password_dialog.py
gui/qt/paytoedit.py
gui/qt/qrcodewidget.py
gui/qt/qrtextedit.py
gui/qt/qrwindow.py
gui/qt/request_list.py
gui/qt/seed_dialog.py
gui/qt/transaction_dialog.py
gui/qt/util.py
gui/qt/utxo_list.py
gui/vtc/__init__.py
gui/vtc/address_dialog.py
gui/vtc/address_list.py
gui/vtc/amountedit.py
gui/vtc/console.py
gui/vtc/contact_list.py
gui/vtc/fee_slider.py
gui/vtc/history_list.py
gui/vtc/icons_rc.py
gui/vtc/installwizard.py
