Metadata-Version: 1.0
Name: Electrum-VTC
Version: 2.9.3.1.post1
Summary: Lightweight Vertcoin Wallet
Home-page: https://github.com/vertcoin/electrum-vtc
Author: James Lovejoy
Author-email: jameslovejoy1@gmail.com
License: MIT Licence
Platform: UNKNOWN
